eflux/__init__.py
eflux/eflux2.py
eflux/utils.py
eflux-0.1.0.dist-info/METADATA
eflux-0.1.0.dist-info/WHEEL
eflux-0.1.0.dist-info/licenses/LICENSE
eflux-0.1.0.dist-info/RECORD
