Metadata-Version: 2.3
Name: eflux
Version: 0.1.0
Summary: Add your description here
License-File: LICENSE
Requires-Python: >=3.8
Requires-Dist: click>=8.1.7
Requires-Dist: cobra>=0.29.0
